parallel_brain/__init__.py
parallel_brain/brain.py
parallel_brain-2.0.4.dist-info/LICENSE
parallel_brain-2.0.4.dist-info/METADATA
parallel_brain-2.0.4.dist-info/WHEEL
parallel_brain-2.0.4.dist-info/top_level.txt
parallel_brain-2.0.4.dist-info/RECORD
