Metadata-Version: 2.1
Name: parallel-brain
Version: 2.0.4
Summary: ParallelBrain ANN with Adaptive Inhibition and Sparse Connectivity
Home-page: https://github.com/yourusername/parallel-brain
Author: Darshan U P
Author-email: darshandileep4@gmail.com
Classifier: Programming Language :: Python :: 3
Classifier: Operating System :: OS Independent
Requires-Python: >=3.6
License-File: LICENSE
